kubos/__init__.py
kubos/build.py
kubos/clean.py
kubos/config.py
kubos/debug.py
kubos/flash.py
kubos/init.py
kubos/licenses.py
kubos/link.py
kubos/list.py
kubos/main.py
kubos/remove.py
kubos/search.py
kubos/server.py
kubos/shrinkwrap.py
kubos/target.py
kubos/test.py
kubos/update.py
kubos/version.py
kubos/bin/linux/dfu-util
kubos/bin/linux/mspdebug
kubos/bin/linux/openocd
kubos/bin/osx/dfu-util
kubos/bin/osx/mspdebug
kubos/bin/osx/openocd
kubos/flash/dfu_util/flash.sh
kubos/flash/mspdebug/flash.sh
kubos/flash/openocd/flash.sh
kubos/flash/openocd/mem_helper.tcl
kubos/flash/openocd/osxusb.py
kubos/flash/openocd/stm32f407g-disc1.cfg
kubos/flash/openocd/stm32f407vg.cfg
kubos/flash/openocd/stm32f4x_stlink.cfg
kubos/flash/openocd/interface/stlink-v2-1.cfg
kubos/flash/openocd/interface/stlink-v2.cfg
kubos/flash/openocd/target/stm32f4x.cfg
kubos/flash/openocd/target/stm32f4x_stlink.cfg
kubos/flash/openocd/target/swj-dp.tcl
kubos/lib/linux/libhidapi-hidraw.so.0
kubos/lib/linux/libmsp430.so
kubos/lib/linux/libudev.so.0
kubos/lib/linux/libusb-1.0.so.0
kubos/lib/osx/libmsp430.dylib
kubos/options/__init__.py
kubos/options/parser.py
kubos/utils/__init__.py
kubos/utils/container.py
kubos/utils/getip.sh
kubos/utils/project.py
kubos/utils/status_spinner.py
kubos/utils/target.py
kubos_sdk-0.0.4.dist-info/DESCRIPTION.rst
kubos_sdk-0.0.4.dist-info/METADATA
kubos_sdk-0.0.4.dist-info/RECORD
kubos_sdk-0.0.4.dist-info/WHEEL
kubos_sdk-0.0.4.dist-info/entry_points.txt
kubos_sdk-0.0.4.dist-info/metadata.json
kubos_sdk-0.0.4.dist-info/top_level.txt
