Metadata-Version: 2.0
Name: kubos-sdk
Version: 0.0.4
Summary: Kubos SDK
Home-page: http://github.com/openkosmosorg/kubos-sdk
Author: Kubos
Author-email: kyle@kubos.co
License: UNKNOWN
Platform: UNKNOWN
Classifier: Programming Language :: Python :: 2
Classifier: Programming Language :: Python :: 2.6
Classifier: Programming Language :: Python :: 2.7
Requires-Dist: docker-py
Requires-Dist: dockerpty
Requires-Dist: psutil
Requires-Dist: setuptools
Requires-Dist: yotta
